deepquant/__init__.py
deepquant/data/__init__.py
deepquant/data/gqclient/__init__.py
deepquant/data/gqclient/commons.py
deepquant/data/gqclient/hclient.py
deepquant/data/gqclient/wsclient.py
deepquant/data/gqclient/wshandler.py
deepquant/data/interface/__init__.py
deepquant/data/interface/dataApi.py
deepquant/data/interface/enum.py
deepquant/data/interface/gid.py
deepquant/data/proto/__init__.py
deepquant/data/proto/base_pb2.py
deepquant/data/proto/common_pb2.py
deepquant/data/proto/data_type_pb2.py
deepquant/data/proto/financial_fun_pb2.py
deepquant/data/proto/market_data_pb2.py
deepquant/data/proto/news_pb2.py
deepquant/data/proto/pb_json_format.py
deepquant/data/proto/proto_utils.py
deepquant/data/proto/real_time_md_pb2.py
deepquant/data/proto/realtime_factor_data_pb2.py
deepquant/data/proto/realtime_factor_server_pb2.py
deepquant/data/proto/replay_pb2.py
deepquant/data/proto/sdk_message_pb2.py
deepquant/data/utils/__init__.py
deepquant/data/utils/encrypt_util.py
deepquant/data/utils/gqconfig.py
deepquant/data/utils/gqconfig_dev.py
deepquant/data/utils/gqconfig_hub.py
deepquant/data/utils/gqconfig_inner.py
deepquant/data/utils/gqconfig_prod.py
deepquant/data/utils/gqconfig_test.py
deepquant/data/utils/gqconfig_uat.py
deepquant/data/utils/log_writer.py
deepquant/docs/银河策略中心_因子分析SDK使用说明.pdf
deepquant/docs/银河策略中心_数据SDK使用说明.pdf
deepquant/docs/银河策略中心使用手册(数据和因子).pdf
deepquant/examples/get_factors.py
deepquant/examples/get_kline.py
deepquant/factor/__init__.py
deepquant/factor/analysor.py
deepquant/factor/calc.py
deepquant/factor/data_desp_default.yaml
deepquant/factor/factor_analyzer.py
deepquant/factor/factor_cal.py
deepquant/factor/factor_parser.py
deepquant/factor/financial_data_clean.py
deepquant/factor/globals.py
deepquant/factor/mgr.py
deepquant/factor/op.py
deepquant/factor/op_udf.py
deepquant/factor/oq_data.py
deepquant/factor/perf.py
deepquant/factor/plotting.py
deepquant/factor/summary.py
deepquant/factor/utils.py
deepquant/oplib/__init__.py
deepquant-0.4.3.dist-info/METADATA
deepquant-0.4.3.dist-info/WHEEL
deepquant-0.4.3.dist-info/top_level.txt
deepquant-0.4.3.dist-info/RECORD
