Metadata-Version: 2.1
Name: deepquant
Version: 0.4.3
Summary: quant data and factor tools by cgs
Author: cgs
Classifier: Programming Language :: Python :: 3
Classifier: License :: OSI Approved :: MIT License
Classifier: Operating System :: OS Independent
Requires-Python: >=3.8
Requires-Dist: requests>=2.25.1
Requires-Dist: numpy<=1.26.4,>=1.19.5
Requires-Dist: pandas>=1.2.0
Requires-Dist: websocket-client
Requires-Dist: protobuf<=3.20.3
Requires-Dist: PyJWT
Requires-Dist: statsmodels
Requires-Dist: scipy
Requires-Dist: pyecharts
Requires-Dist: empyrical-reloaded
Requires-Dist: astor
Requires-Dist: RestrictedPython
Requires-Dist: pyyaml
Provides-Extra: dev
Requires-Dist: pytest>=6.2.2; extra == "dev"
Requires-Dist: sphinx>=3.4.3; extra == "dev"
